calculator/__init__.py
calculator/calculator.py
ablilcalculator-0.0.3.dist-info/LICENSE
ablilcalculator-0.0.3.dist-info/METADATA
ablilcalculator-0.0.3.dist-info/WHEEL
ablilcalculator-0.0.3.dist-info/top_level.txt
ablilcalculator-0.0.3.dist-info/RECORD
