Metadata-Version: 2.1
Name: ablilcalculator
Version: 0.0.3
Summary: short description here
Author-email: ablil <ablil@pm.me>
Project-URL: Homepage, https://github.com/pypa/sampleproject
Project-URL: Bug Tracker, https://github.com/pypa/sampleproject/issues
Keywords: calculator,math
Classifier: Programming Language :: Python :: 3
Classifier: Operating System :: OS Independent
Requires-Python: >=3.7
License-File: LICENSE
Requires-Dist: requests
